convect_flow_sdk/__init__.py
convect_flow_sdk/cli.py
convect_flow_sdk/constants.py
convect_flow_sdk/flow_algo.py
convect_flow_sdk/flow_app.py
convect_flow_sdk-0.0.6.dist-info/LICENSE
convect_flow_sdk-0.0.6.dist-info/METADATA
convect_flow_sdk-0.0.6.dist-info/WHEEL
convect_flow_sdk-0.0.6.dist-info/entry_points.txt
convect_flow_sdk-0.0.6.dist-info/top_level.txt
convect_flow_sdk-0.0.6.dist-info/RECORD
