Metadata-Version: 2.1
Name: convect-flow-sdk
Version: 0.0.6
Summary: convect flow sdk
Home-page: https://github.com/convect-ai/flow-sdk
Author: convect.ai
Author-email: hi@convect.ai
License: UNKNOWN
Platform: UNKNOWN
Requires-Python: >=3.9
License-File: LICENSE
Requires-Dist: requests
Requires-Dist: click >=8.0.1
Provides-Extra: tests
Requires-Dist: pytest ~=6.1 ; extra == 'tests'
Requires-Dist: pytest-mock ~=3.6.1 ; extra == 'tests'
